t50metrics/__init__.py
t50metrics-0.1.0.dist-info/LICENSE
t50metrics-0.1.0.dist-info/METADATA
t50metrics-0.1.0.dist-info/WHEEL
t50metrics-0.1.0.dist-info/top_level.txt
t50metrics-0.1.0.dist-info/RECORD
